titus_optimize/__init__.py
titus_optimize/benchmark.py
titus_optimize/compute.py
titus_optimize/compute_v2.py
titus_optimize/compute_v3.py
titus_optimize/compute_v4.py
titus_optimize/data.py
titus_optimize/encoders.py
titus_optimize/eval.py
titus_optimize/predictors.py
titus_optimize/utils.py
titus_optimize-0.7.7.dist-info/DESCRIPTION.rst
titus_optimize-0.7.7.dist-info/METADATA
titus_optimize-0.7.7.dist-info/RECORD
titus_optimize-0.7.7.dist-info/WHEEL
titus_optimize-0.7.7.dist-info/metadata.json
titus_optimize-0.7.7.dist-info/top_level.txt
