Metadata-Version: 2.0
Name: titus-optimize
Version: 0.7.7
Summary: A package for optimizing placements of containers.
Home-page: https://github.com/Netflix-Skunkworks/titus-optimize
Author: titus
Author-email: titus-ops@netflix.com
License: UNKNOWN
Keywords: titus
Platform: UNKNOWN
Requires-Python: >=3.5
Provides-Extra: test
Requires-Dist: cvxpy (==1.1.5)
Requires-Dist: lightgbm (==2.2.3)
Requires-Dist: numpy (<=1.19.4,>=1.16)
Requires-Dist: pandas (==0.24.1)
Provides-Extra: test
Requires-Dist: tox; extra == 'test'
